{
  "chainId": 101,
  "address": "GnLRNPeKca4FX6rAAc8JQeY6Wx5AqGbA3QP9ZqiTsBvS",
  "symbol": "CAI",
  "name": "CAICoin",
  "decimals": 6,
  "logoURI": "https://raw.githubusercontent.com/caicoin/token-list/main/assets/mainnet/GnLRNPeKca4FX6rAAc8JQeY6Wx5AqGbA3QP9ZqiTsBvS/logo.png",
  "tags": ["utility-token"],
  "extensions": {
    "twitter": "https://x.com/caicoin2020",
    "description": "CAICoin is a utility token designed to bridge real-world value with Web3 services, symbolizing both heritage and innovation.财币是一种实用代币，旨在将现实世界的价值与 Web3 服务联系起来，象征着传承与创新。"
  }
}
